{
    "latitude": 32.883421,
    "longitude": -97.274044,
    "timezone": "America/Chicago",
    "offset": -5,
    "currently": {
        "time": 1493656722,
        "summary": "Clear",
        "icon": "clear-day",
        "nearestStormDistance": 347,
        "nearestStormBearing": 37,
        "precipIntensity": 0,
        "precipProbability": 0,
        "temperature": 77.87,
        "apparentTemperature": 77.87,
        "dewPoint": 50.93,
        "humidity": 0.39,
        "windSpeed": 6.37,
        "windBearing": 216,
        "visibility": 10,
        "cloudCover": 0,
        "pressure": 1014.23,
        "ozone": 311.83
    },
    "minutely": {
        "summary": "Clear for the hour.",
        "icon": "clear-day",
        "data": [{
            "time": 1493656680,
            "precipIntensity": 0,
            "precipProbability": 0
        }, {
            "time": 1493656740,
            "precipIntensity": 0,
            "precipProbability": 0
        }, {
            "time": 1493656800,
            "precipIntensity": 0,
            "precipProbability": 0
        }, {
            "time": 1493656860,
            "precipIntensity": 0,
            "precipProbability": 0
        }, {
            "time": 1493656920,
            "precipIntensity": 0,
            "precipProbability": 0
        }, {
            "time": 1493656980,
            "precipIntensity": 0,
            "precipProbability": 0
        }, {
            "time": 1493657040,
            "precipIntensity": 0,
            "precipProbability": 0
        }, {
            "time": 1493657100,
            "precipIntensity": 0,
            "precipProbability": 0
        }, {
            "time": 1493657160,
            "precipIntensity": 0,
            "precipProbability": 0
        }, {
            "time": 1493657220,
            "precipIntensity": 0,
            "precipProbability": 0
        }, {
            "time": 1493657280,
            "precipIntensity": 0,
            "precipProbability": 0
        }, {
            "time": 1493657340,
            "precipIntensity": 0,
            "precipProbability": 0
        }, {
            "time": 1493657400,
            "precipIntensity": 0,
            "precipProbability": 0
        }, {
            "time": 1493657460,
            "precipIntensity": 0,
            "precipProbability": 0
        }, {
            "time": 1493657520,
            "precipIntensity": 0,
            "precipProbability": 0
        }, {
            "time": 1493657580,
            "precipIntensity": 0,
            "precipProbability": 0
        }, {
            "time": 1493657640,
            "precipIntensity": 0,
            "precipProbability": 0
        }, {
            "time": 1493657700,
            "precipIntensity": 0,
            "precipProbability": 0
        }, {
            "time": 1493657760,
            "precipIntensity": 0,
            "precipProbability": 0
        }, {
            "time": 1493657820,
            "precipIntensity": 0,
            "precipProbability": 0
        }, {
            "time": 1493657880,
            "precipIntensity": 0,
            "precipProbability": 0
        }, {
            "time": 1493657940,
            "precipIntensity": 0,
            "precipProbability": 0
        }, {
            "time": 1493658000,
            "precipIntensity": 0,
            "precipProbability": 0
        }, {
            "time": 1493658060,
            "precipIntensity": 0,
            "precipProbability": 0
        }, {
            "time": 1493658120,
            "precipIntensity": 0,
            "precipProbability": 0
        }, {
            "time": 1493658180,
            "precipIntensity": 0,
            "precipProbability": 0
        }, {
            "time": 1493658240,
            "precipIntensity": 0,
            "precipProbability": 0
        }, {
            "time": 1493658300,
            "precipIntensity": 0,
            "precipProbability": 0
        }, {
            "time": 1493658360,
            "precipIntensity": 0,
            "precipProbability": 0
        }, {
            "time": 1493658420,
            "precipIntensity": 0,
            "precipProbability": 0
        }, {
            "time": 1493658480,
            "precipIntensity": 0,
            "precipProbability": 0
        }, {
            "time": 1493658540,
            "precipIntensity": 0,
            "precipProbability": 0
        }, {
            "time": 1493658600,
            "precipIntensity": 0,
            "precipProbability": 0
        }, {
            "time": 1493658660,
            "precipIntensity": 0,
            "precipProbability": 0
        }, {
            "time": 1493658720,
            "precipIntensity": 0,
            "precipProbability": 0
        }, {
            "time": 1493658780,
            "precipIntensity": 0,
            "precipProbability": 0
        }, {
            "time": 1493658840,
            "precipIntensity": 0,
            "precipProbability": 0
        }, {
            "time": 1493658900,
            "precipIntensity": 0,
            "precipProbability": 0
        }, {
            "time": 1493658960,
            "precipIntensity": 0,
            "precipProbability": 0
        }, {
            "time": 1493659020,
            "precipIntensity": 0,
            "precipProbability": 0
        }, {
            "time": 1493659080,
            "precipIntensity": 0,
            "precipProbability": 0
        }, {
            "time": 1493659140,
            "precipIntensity": 0,
            "precipProbability": 0
        }, {
            "time": 1493659200,
            "precipIntensity": 0,
            "precipProbability": 0
        }, {
            "time": 1493659260,
            "precipIntensity": 0,
            "precipProbability": 0
        }, {
            "time": 1493659320,
            "precipIntensity": 0,
            "precipProbability": 0
        }, {
            "time": 1493659380,
            "precipIntensity": 0,
            "precipProbability": 0
        }, {
            "time": 1493659440,
            "precipIntensity": 0,
            "precipProbability": 0
        }, {
            "time": 1493659500,
            "precipIntensity": 0,
            "precipProbability": 0
        }, {
            "time": 1493659560,
            "precipIntensity": 0,
            "precipProbability": 0
        }, {
            "time": 1493659620,
            "precipIntensity": 0,
            "precipProbability": 0
        }, {
            "time": 1493659680,
            "precipIntensity": 0,
            "precipProbability": 0
        }, {
            "time": 1493659740,
            "precipIntensity": 0,
            "precipProbability": 0
        }, {
            "time": 1493659800,
            "precipIntensity": 0,
            "precipProbability": 0
        }, {
            "time": 1493659860,
            "precipIntensity": 0,
            "precipProbability": 0
        }, {
            "time": 1493659920,
            "precipIntensity": 0,
            "precipProbability": 0
        }, {
            "time": 1493659980,
            "precipIntensity": 0,
            "precipProbability": 0
        }, {
            "time": 1493660040,
            "precipIntensity": 0,
            "precipProbability": 0
        }, {
            "time": 1493660100,
            "precipIntensity": 0,
            "precipProbability": 0
        }, {
            "time": 1493660160,
            "precipIntensity": 0,
            "precipProbability": 0
        }, {
            "time": 1493660220,
            "precipIntensity": 0,
            "precipProbability": 0
        }, {
            "time": 1493660280,
            "precipIntensity": 0,
            "precipProbability": 0
        }]
    },
    "hourly": {
        "summary": "Clear throughout the day.",
        "icon": "clear-day",
        "data": [{
            "time": 1493654400,
            "summary": "Clear",
            "icon": "clear-day",
            "precipIntensity": 0,
            "precipProbability": 0,
            "temperature": 66.51,
            "apparentTemperature": 66.51,
            "dewPoint": 42.52,
            "humidity": 0.42,
            "windSpeed": 5.75,
            "windBearing": 213,
            "visibility": 10,
            "cloudCover": 0,
            "pressure": 1014.25,
            "ozone": 312.07
        }, {
            "time": 1493658000,
            "summary": "Clear",
            "icon": "clear-day",
            "precipIntensity": 0,
            "precipProbability": 0,
            "temperature": 77.87,
            "apparentTemperature": 77.87,
            "dewPoint": 49.9,
            "humidity": 0.38,
            "windSpeed": 6.71,
            "windBearing": 217,
            "visibility": 10,
            "cloudCover": 0,
            "pressure": 1014.22,
            "ozone": 311.7
        }, {
            "time": 1493661600,
            "summary": "Clear",
            "icon": "clear-day",
            "precipIntensity": 0,
            "precipProbability": 0,
            "temperature": 79.55,
            "apparentTemperature": 79.55,
            "dewPoint": 48.51,
            "humidity": 0.34,
            "windSpeed": 7.62,
            "windBearing": 223,
            "visibility": 10,
            "cloudCover": 0,
            "pressure": 1014.14,
            "ozone": 311.14
        }, {
            "time": 1493665200,
            "summary": "Clear",
            "icon": "clear-day",
            "precipIntensity": 0,
            "precipProbability": 0,
            "temperature": 80.89,
            "apparentTemperature": 79.8,
            "dewPoint": 47.3,
            "humidity": 0.31,
            "windSpeed": 7.28,
            "windBearing": 229,
            "visibility": 10,
            "cloudCover": 0,
            "pressure": 1013.86,
            "ozone": 310.07
        }, {
            "time": 1493668800,
            "summary": "Clear",
            "icon": "clear-day",
            "precipIntensity": 0,
            "precipProbability": 0,
            "temperature": 82.43,
            "apparentTemperature": 80.71,
            "dewPoint": 46.94,
            "humidity": 0.29,
            "windSpeed": 6.01,
            "windBearing": 235,
            "visibility": 10,
            "cloudCover": 0.01,
            "pressure": 1013.28,
            "ozone": 308.81
        }, {
            "time": 1493672400,
            "summary": "Clear",
            "icon": "clear-day",
            "precipIntensity": 0,
            "precipProbability": 0,
            "temperature": 83.22,
            "apparentTemperature": 81.24,
            "dewPoint": 46.93,
            "humidity": 0.28,
            "windSpeed": 4.21,
            "windBearing": 241,
            "visibility": 10,
            "cloudCover": 0.01,
            "pressure": 1012.66,
            "ozone": 307.74
        }, {
            "time": 1493676000,
            "summary": "Clear",
            "icon": "clear-day",
            "precipIntensity": 0,
            "precipProbability": 0,
            "temperature": 82.95,
            "apparentTemperature": 80.98,
            "dewPoint": 46.06,
            "humidity": 0.28,
            "windSpeed": 1.53,
            "windBearing": 260,
            "visibility": 10,
            "cloudCover": 0.01,
            "pressure": 1011.95,
            "ozone": 307.05
        }, {
            "time": 1493679600,
            "summary": "Clear",
            "icon": "clear-day",
            "precipIntensity": 0,
            "precipProbability": 0,
            "temperature": 81.13,
            "apparentTemperature": 79.79,
            "dewPoint": 45.36,
            "humidity": 0.28,
            "windSpeed": 1.72,
            "windBearing": 43,
            "visibility": 10,
            "cloudCover": 0.01,
            "pressure": 1011.64,
            "ozone": 306.53
        }, {
            "time": 1493683200,
            "summary": "Clear",
            "icon": "clear-day",
            "precipIntensity": 0,
            "precipProbability": 0,
            "temperature": 78.04,
            "apparentTemperature": 78.04,
            "dewPoint": 44.96,
            "humidity": 0.31,
            "windSpeed": 4.22,
            "windBearing": 58,
            "visibility": 10,
            "cloudCover": 0.01,
            "pressure": 1011.58,
            "ozone": 306.01
        }, {
            "time": 1493686800,
            "summary": "Clear",
            "icon": "clear-day",
            "precipIntensity": 0,
            "precipProbability": 0,
            "temperature": 73.15,
            "apparentTemperature": 73.15,
            "dewPoint": 44.9,
            "humidity": 0.36,
            "windSpeed": 5.24,
            "windBearing": 64,
            "visibility": 10,
            "cloudCover": 0.02,
            "pressure": 1011.92,
            "ozone": 305.5
        }, {
            "time": 1493690400,
            "summary": "Clear",
            "icon": "clear-night",
            "precipIntensity": 0,
            "precipProbability": 0,
            "temperature": 68.58,
            "apparentTemperature": 68.58,
            "dewPoint": 45.07,
            "humidity": 0.43,
            "windSpeed": 5.36,
            "windBearing": 69,
            "visibility": 10,
            "cloudCover": 0.02,
            "pressure": 1012.49,
            "ozone": 304.97
        }, {
            "time": 1493694000,
            "summary": "Clear",
            "icon": "clear-night",
            "precipIntensity": 0,
            "precipProbability": 0,
            "temperature": 65.71,
            "apparentTemperature": 65.71,
            "dewPoint": 45.59,
            "humidity": 0.48,
            "windSpeed": 5.69,
            "windBearing": 74,
            "visibility": 10,
            "cloudCover": 0.03,
            "pressure": 1013.01,
            "ozone": 304.23
        }, {
            "time": 1493697600,
            "summary": "Clear",
            "icon": "clear-night",
            "precipIntensity": 0,
            "precipProbability": 0,
            "temperature": 63.64,
            "apparentTemperature": 63.64,
            "dewPoint": 46.52,
            "humidity": 0.54,
            "windSpeed": 5.61,
            "windBearing": 77,
            "visibility": 10,
            "cloudCover": 0.03,
            "pressure": 1013.37,
            "ozone": 303.14
        }, {
            "time": 1493701200,
            "summary": "Clear",
            "icon": "clear-night",
            "precipIntensity": 0,
            "precipProbability": 0,
            "temperature": 62.25,
            "apparentTemperature": 62.25,
            "dewPoint": 47.35,
            "humidity": 0.58,
            "windSpeed": 5.48,
            "windBearing": 80,
            "visibility": 10,
            "cloudCover": 0.04,
            "pressure": 1013.66,
            "ozone": 301.82
        }, {
            "time": 1493704800,
            "summary": "Clear",
            "icon": "clear-night",
            "precipIntensity": 0,
            "precipProbability": 0,
            "temperature": 61.14,
            "apparentTemperature": 61.14,
            "dewPoint": 48.47,
            "humidity": 0.63,
            "windSpeed": 5.31,
            "windBearing": 86,
            "visibility": 10,
            "cloudCover": 0.03,
            "pressure": 1013.82,
            "ozone": 300.47
        }, {
            "time": 1493708400,
            "summary": "Clear",
            "icon": "clear-night",
            "precipIntensity": 0,
            "precipProbability": 0,
            "temperature": 60.27,
            "apparentTemperature": 60.27,
            "dewPoint": 49.3,
            "humidity": 0.67,
            "windSpeed": 5.53,
            "windBearing": 97,
            "visibility": 10,
            "cloudCover": 0.08,
            "pressure": 1013.74,
            "ozone": 298.98
        }, {
            "time": 1493712000,
            "summary": "Clear",
            "icon": "clear-night",
            "precipIntensity": 0,
            "precipProbability": 0,
            "temperature": 59.55,
            "apparentTemperature": 59.55,
            "dewPoint": 50.01,
            "humidity": 0.71,
            "windSpeed": 5.94,
            "windBearing": 111,
            "visibility": 10,
            "cloudCover": 0.16,
            "pressure": 1013.53,
            "ozone": 297.45
        }, {
            "time": 1493715600,
            "summary": "Clear",
            "icon": "clear-night",
            "precipIntensity": 0,
            "precipProbability": 0,
            "temperature": 58.9,
            "apparentTemperature": 58.9,
            "dewPoint": 50.45,
            "humidity": 0.74,
            "windSpeed": 6.41,
            "windBearing": 122,
            "visibility": 9.86,
            "cloudCover": 0.22,
            "pressure": 1013.41,
            "ozone": 296.34
        }, {
            "time": 1493719200,
            "summary": "Clear",
            "icon": "clear-night",
            "precipIntensity": 0,
            "precipProbability": 0,
            "temperature": 58.15,
            "apparentTemperature": 58.15,
            "dewPoint": 51.17,
            "humidity": 0.78,
            "windSpeed": 6.61,
            "windBearing": 129,
            "visibility": 9.91,
            "cloudCover": 0.22,
            "pressure": 1013.55,
            "ozone": 295.96
        }, {
            "time": 1493722800,
            "summary": "Clear",
            "icon": "clear-night",
            "precipIntensity": 0,
            "precipProbability": 0,
            "temperature": 56.88,
            "apparentTemperature": 56.88,
            "dewPoint": 51.27,
            "humidity": 0.81,
            "windSpeed": 6.72,
            "windBearing": 140,
            "visibility": 9.95,
            "cloudCover": 0.23,
            "pressure": 1013.81,
            "ozone": 296
        }, {
            "time": 1493726400,
            "summary": "Clear",
            "icon": "clear-day",
            "precipIntensity": 0,
            "precipProbability": 0,
            "temperature": 57.25,
            "apparentTemperature": 57.25,
            "dewPoint": 51.81,
            "humidity": 0.82,
            "windSpeed": 6.77,
            "windBearing": 153,
            "visibility": 9.97,
            "cloudCover": 0.23,
            "pressure": 1014.05,
            "ozone": 295.98
        }, {
            "time": 1493730000,
            "summary": "Clear",
            "icon": "clear-day",
            "precipIntensity": 0,
            "precipProbability": 0,
            "temperature": 60.62,
            "apparentTemperature": 60.62,
            "dewPoint": 53.56,
            "humidity": 0.78,
            "windSpeed": 7.13,
            "windBearing": 168,
            "visibility": 9.96,
            "cloudCover": 0.2,
            "pressure": 1014.32,
            "ozone": 295.69
        }, {
            "time": 1493733600,
            "summary": "Clear",
            "icon": "clear-day",
            "precipIntensity": 0,
            "precipProbability": 0,
            "temperature": 65.63,
            "apparentTemperature": 65.63,
            "dewPoint": 54.53,
            "humidity": 0.67,
            "windSpeed": 8.75,
            "windBearing": 185,
            "visibility": 10,
            "cloudCover": 0.15,
            "pressure": 1014.59,
            "ozone": 295.35
        }, {
            "time": 1493737200,
            "summary": "Clear",
            "icon": "clear-day",
            "precipIntensity": 0,
            "precipProbability": 0,
            "temperature": 70.88,
            "apparentTemperature": 70.88,
            "dewPoint": 54.77,
            "humidity": 0.57,
            "windSpeed": 9.79,
            "windBearing": 192,
            "visibility": 10,
            "cloudCover": 0.03,
            "pressure": 1014.68,
            "ozone": 295.13
        }, {
            "time": 1493740800,
            "summary": "Clear",
            "icon": "clear-day",
            "precipIntensity": 0,
            "precipProbability": 0,
            "temperature": 75.24,
            "apparentTemperature": 75.24,
            "dewPoint": 55.43,
            "humidity": 0.5,
            "windSpeed": 10.33,
            "windBearing": 192,
            "visibility": 10,
            "cloudCover": 0.03,
            "pressure": 1014.53,
            "ozone": 295.13
        }, {
            "time": 1493744400,
            "summary": "Clear",
            "icon": "clear-day",
            "precipIntensity": 0,
            "precipProbability": 0,
            "temperature": 79.21,
            "apparentTemperature": 79.21,
            "dewPoint": 56.42,
            "humidity": 0.46,
            "windSpeed": 10.52,
            "windBearing": 187,
            "visibility": 10,
            "cloudCover": 0.03,
            "pressure": 1014.2,
            "ozone": 295.26
        }, {
            "time": 1493748000,
            "summary": "Clear",
            "icon": "clear-day",
            "precipIntensity": 0,
            "precipProbability": 0,
            "temperature": 82.81,
            "apparentTemperature": 82.35,
            "dewPoint": 56.92,
            "humidity": 0.41,
            "windSpeed": 10.93,
            "windBearing": 183,
            "visibility": 10,
            "cloudCover": 0.02,
            "pressure": 1013.69,
            "ozone": 295.48
        }, {
            "time": 1493751600,
            "summary": "Clear",
            "icon": "clear-day",
            "precipIntensity": 0,
            "precipProbability": 0,
            "temperature": 85.41,
            "apparentTemperature": 84.51,
            "dewPoint": 57.31,
            "humidity": 0.39,
            "windSpeed": 11.85,
            "windBearing": 179,
            "visibility": 10,
            "cloudCover": 0.01,
            "pressure": 1012.93,
            "ozone": 295.79
        }, {
            "time": 1493755200,
            "summary": "Clear",
            "icon": "clear-day",
            "precipIntensity": 0,
            "precipProbability": 0,
            "temperature": 86.92,
            "apparentTemperature": 86.01,
            "dewPoint": 57.96,
            "humidity": 0.38,
            "windSpeed": 12.98,
            "windBearing": 174,
            "visibility": 10,
            "cloudCover": 0,
            "pressure": 1011.97,
            "ozone": 296.19
        }, {
            "time": 1493758800,
            "summary": "Clear",
            "icon": "clear-day",
            "precipIntensity": 0,
            "precipProbability": 0,
            "temperature": 88.52,
            "apparentTemperature": 87.91,
            "dewPoint": 59.25,
            "humidity": 0.37,
            "windSpeed": 13.85,
            "windBearing": 170,
            "visibility": 10,
            "cloudCover": 0,
            "pressure": 1011.11,
            "ozone": 296.57
        }, {
            "time": 1493762400,
            "summary": "Clear",
            "icon": "clear-day",
            "precipIntensity": 0,
            "precipProbability": 0,
            "temperature": 88.08,
            "apparentTemperature": 87.81,
            "dewPoint": 60.14,
            "humidity": 0.39,
            "windSpeed": 14.02,
            "windBearing": 166,
            "visibility": 10,
            "cloudCover": 0.03,
            "pressure": 1010.41,
            "ozone": 296.91
        }, {
            "time": 1493766000,
            "summary": "Clear",
            "icon": "clear-day",
            "precipIntensity": 0,
            "precipProbability": 0,
            "temperature": 86.16,
            "apparentTemperature": 86.05,
            "dewPoint": 60.32,
            "humidity": 0.42,
            "windSpeed": 13.73,
            "windBearing": 162,
            "visibility": 10,
            "cloudCover": 0.06,
            "pressure": 1009.87,
            "ozone": 297.23
        }, {
            "time": 1493769600,
            "summary": "Clear",
            "icon": "clear-day",
            "precipIntensity": 0,
            "precipProbability": 0,
            "temperature": 83.04,
            "apparentTemperature": 83.13,
            "dewPoint": 59.58,
            "humidity": 0.45,
            "windSpeed": 13.71,
            "windBearing": 159,
            "visibility": 10,
            "cloudCover": 0.12,
            "pressure": 1009.57,
            "ozone": 297.47
        }, {
            "time": 1493773200,
            "summary": "Clear",
            "icon": "clear-day",
            "precipIntensity": 0,
            "precipProbability": 0,
            "temperature": 79.81,
            "apparentTemperature": 79.81,
            "dewPoint": 58.97,
            "humidity": 0.49,
            "windSpeed": 13.3,
            "windBearing": 155,
            "visibility": 10,
            "cloudCover": 0.21,
            "pressure": 1009.63,
            "ozone": 297.59
        }, {
            "time": 1493776800,
            "summary": "Partly Cloudy",
            "icon": "partly-cloudy-night",
            "precipIntensity": 0,
            "precipProbability": 0,
            "temperature": 76.73,
            "apparentTemperature": 76.73,
            "dewPoint": 58.53,
            "humidity": 0.53,
            "windSpeed": 12.74,
            "windBearing": 152,
            "visibility": 10,
            "cloudCover": 0.33,
            "pressure": 1009.93,
            "ozone": 297.62
        }, {
            "time": 1493780400,
            "summary": "Partly Cloudy",
            "icon": "partly-cloudy-night",
            "precipIntensity": 0,
            "precipProbability": 0,
            "temperature": 74.04,
            "apparentTemperature": 74.04,
            "dewPoint": 57.71,
            "humidity": 0.57,
            "windSpeed": 12.53,
            "windBearing": 152,
            "visibility": 10,
            "cloudCover": 0.41,
            "pressure": 1010.24,
            "ozone": 297.56
        }, {
            "time": 1493784000,
            "summary": "Partly Cloudy",
            "icon": "partly-cloudy-night",
            "precipIntensity": 0,
            "precipProbability": 0,
            "temperature": 72.15,
            "apparentTemperature": 72.15,
            "dewPoint": 56.38,
            "humidity": 0.58,
            "windSpeed": 13.48,
            "windBearing": 156,
            "visibility": 10,
            "cloudCover": 0.44,
            "pressure": 1010.51,
            "ozone": 297.36
        }, {
            "time": 1493787600,
            "summary": "Partly Cloudy",
            "icon": "partly-cloudy-night",
            "precipIntensity": 0,
            "precipProbability": 0,
            "temperature": 70.77,
            "apparentTemperature": 70.77,
            "dewPoint": 55,
            "humidity": 0.57,
            "windSpeed": 15.12,
            "windBearing": 161,
            "visibility": 10,
            "cloudCover": 0.44,
            "pressure": 1010.68,
            "ozone": 297.08
        }, {
            "time": 1493791200,
            "summary": "Partly Cloudy",
            "icon": "partly-cloudy-night",
            "precipIntensity": 0,
            "precipProbability": 0,
            "temperature": 69.58,
            "apparentTemperature": 69.58,
            "dewPoint": 54.44,
            "humidity": 0.59,
            "windSpeed": 16.32,
            "windBearing": 166,
            "visibility": 10,
            "cloudCover": 0.46,
            "pressure": 1010.65,
            "ozone": 296.9
        }, {
            "time": 1493794800,
            "summary": "Partly Cloudy",
            "icon": "partly-cloudy-night",
            "precipIntensity": 0,
            "precipProbability": 0,
            "temperature": 68.24,
            "apparentTemperature": 68.24,
            "dewPoint": 54.89,
            "humidity": 0.62,
            "windSpeed": 16.5,
            "windBearing": 169,
            "visibility": 10,
            "cloudCover": 0.56,
            "pressure": 1010.31,
            "ozone": 296.79
        }, {
            "time": 1493798400,
            "summary": "Mostly Cloudy",
            "icon": "partly-cloudy-night",
            "precipIntensity": 0,
            "precipProbability": 0,
            "temperature": 66.97,
            "apparentTemperature": 66.97,
            "dewPoint": 55.87,
            "humidity": 0.68,
            "windSpeed": 16.07,
            "windBearing": 173,
            "visibility": 10,
            "cloudCover": 0.7,
            "pressure": 1009.81,
            "ozone": 296.79
        }, {
            "time": 1493802000,
            "summary": "Mostly Cloudy",
            "icon": "partly-cloudy-night",
            "precipIntensity": 0,
            "precipProbability": 0,
            "temperature": 66.03,
            "apparentTemperature": 66.03,
            "dewPoint": 57.07,
            "humidity": 0.73,
            "windSpeed": 15.67,
            "windBearing": 175,
            "visibility": 10,
            "cloudCover": 0.8,
            "pressure": 1009.37,
            "ozone": 297.21
        }, {
            "time": 1493805600,
            "summary": "Mostly Cloudy",
            "icon": "partly-cloudy-night",
            "precipIntensity": 0,
            "precipProbability": 0,
            "temperature": 65.37,
            "apparentTemperature": 65.37,
            "dewPoint": 58.51,
            "humidity": 0.79,
            "windSpeed": 15.36,
            "windBearing": 177,
            "visibility": 10,
            "cloudCover": 0.85,
            "pressure": 1009,
            "ozone": 298.37
        }, {
            "time": 1493809200,
            "summary": "Mostly Cloudy",
            "icon": "partly-cloudy-night",
            "precipIntensity": 0,
            "precipProbability": 0,
            "temperature": 64.99,
            "apparentTemperature": 64.99,
            "dewPoint": 60.11,
            "humidity": 0.84,
            "windSpeed": 14.66,
            "windBearing": 176,
            "visibility": 10,
            "cloudCover": 0.89,
            "pressure": 1008.7,
            "ozone": 299.97
        }, {
            "time": 1493812800,
            "summary": "Mostly Cloudy",
            "icon": "partly-cloudy-day",
            "precipIntensity": 0,
            "precipProbability": 0,
            "temperature": 65.32,
            "apparentTemperature": 65.32,
            "dewPoint": 61.75,
            "humidity": 0.88,
            "windSpeed": 13.57,
            "windBearing": 177,
            "visibility": 10,
            "cloudCover": 0.91,
            "pressure": 1008.62,
            "ozone": 301.34
        }, {
            "time": 1493816400,
            "summary": "Mostly Cloudy",
            "icon": "partly-cloudy-day",
            "precipIntensity": 0.0047,
            "precipProbability": 0.19,
            "precipType": "rain",
            "temperature": 66.77,
            "apparentTemperature": 66.77,
            "dewPoint": 63.62,
            "humidity": 0.9,
            "windSpeed": 12.42,
            "windBearing": 177,
            "visibility": 7.68,
            "cloudCover": 0.93,
            "pressure": 1008.94,
            "ozone": 302.32
        }, {
            "time": 1493820000,
            "summary": "Light Rain",
            "icon": "rain",
            "precipIntensity": 0.0108,
            "precipProbability": 0.52,
            "precipType": "rain",
            "temperature": 68.8,
            "apparentTemperature": 68.8,
            "dewPoint": 65.52,
            "humidity": 0.89,
            "windSpeed": 11,
            "windBearing": 178,
            "visibility": 4.54,
            "cloudCover": 0.93,
            "pressure": 1009.54,
            "ozone": 303.08
        }, {
            "time": 1493823600,
            "summary": "Light Rain",
            "icon": "rain",
            "precipIntensity": 0.018,
            "precipProbability": 0.59,
            "precipType": "rain",
            "temperature": 70.71,
            "apparentTemperature": 70.71,
            "dewPoint": 67.12,
            "humidity": 0.88,
            "windSpeed": 9,
            "windBearing": 184,
            "visibility": 2.61,
            "cloudCover": 0.94,
            "pressure": 1009.98,
            "ozone": 303.55
        }, {
            "time": 1493827200,
            "summary": "Light Rain",
            "icon": "rain",
            "precipIntensity": 0.0286,
            "precipProbability": 0.65,
            "precipType": "rain",
            "temperature": 72.2,
            "apparentTemperature": 72.2,
            "dewPoint": 68.32,
            "humidity": 0.88,
            "windSpeed": 7.18,
            "windBearing": 202,
            "visibility": 3.24,
            "cloudCover": 0.95,
            "pressure": 1009.91,
            "ozone": 303.23
        }]
    },
    "daily": {
        "summary": "Light rain on Wednesday, with temperatures falling to 75°F on Wednesday.",
        "icon": "rain",
        "data": [{
            "time": 1493614800,
            "summary": "Clear throughout the day.",
            "icon": "clear-day",
            "sunriseTime": 1493638960,
            "sunsetTime": 1493687523,
            "moonPhase": 0.2,
            "precipIntensity": 0,
            "precipIntensityMax": 0,
            "precipProbability": 0,
            "temperatureMin": 43.55,
            "temperatureMinTime": 1493636400,
            "temperatureMax": 83.22,
            "temperatureMaxTime": 1493672400,
            "apparentTemperatureMin": 42.88,
            "apparentTemperatureMinTime": 1493632800,
            "apparentTemperatureMax": 81.24,
            "apparentTemperatureMaxTime": 1493672400,
            "dewPoint": 41.96,
            "humidity": 0.49,
            "windSpeed": 1.79,
            "windBearing": 240,
            "visibility": 9.99,
            "cloudCover": 0.01,
            "pressure": 1013.35,
            "ozone": 312.5
        }, {
            "time": 1493701200,
            "summary": "Partly cloudy starting in the evening.",
            "icon": "partly-cloudy-night",
            "sunriseTime": 1493725303,
            "sunsetTime": 1493773968,
            "moonPhase": 0.23,
            "precipIntensity": 0,
            "precipIntensityMax": 0,
            "precipProbability": 0,
            "temperatureMin": 56.88,
            "temperatureMinTime": 1493722800,
            "temperatureMax": 88.52,
            "temperatureMaxTime": 1493758800,
            "apparentTemperatureMin": 56.88,
            "apparentTemperatureMinTime": 1493722800,
            "apparentTemperatureMax": 87.91,
            "apparentTemperatureMaxTime": 1493758800,
            "dewPoint": 54.9,
            "humidity": 0.57,
            "windSpeed": 8.94,
            "windBearing": 160,
            "visibility": 9.99,
            "cloudCover": 0.14,
            "pressure": 1012.57,
            "ozone": 296.89
        }, {
            "time": 1493787600,
            "summary": "Light rain until afternoon.",
            "icon": "rain",
            "sunriseTime": 1493811647,
            "sunsetTime": 1493860413,
            "moonPhase": 0.27,
            "precipIntensity": 0.0089,
            "precipIntensityMax": 0.0442,
            "precipIntensityMaxTime": 1493834400,
            "precipProbability": 0.71,
            "precipType": "rain",
            "temperatureMin": 58.36,
            "temperatureMinTime": 1493870400,
            "temperatureMax": 74.8,
            "temperatureMaxTime": 1493841600,
            "apparentTemperatureMin": 58.36,
            "apparentTemperatureMinTime": 1493870400,
            "apparentTemperatureMax": 74.8,
            "apparentTemperatureMaxTime": 1493841600,
            "dewPoint": 60.17,
            "humidity": 0.75,
            "windSpeed": 2.73,
            "windBearing": 241,
            "visibility": 7.64,
            "cloudCover": 0.67,
            "pressure": 1010.71,
            "ozone": 309.48
        }, {
            "time": 1493874000,
            "summary": "Partly cloudy until afternoon.",
            "icon": "partly-cloudy-day",
            "sunriseTime": 1493897992,
            "sunsetTime": 1493946859,
            "moonPhase": 0.3,
            "precipIntensity": 0,
            "precipIntensityMax": 0,
            "precipProbability": 0,
            "temperatureMin": 51.35,
            "temperatureMinTime": 1493895600,
            "temperatureMax": 75.5,
            "temperatureMaxTime": 1493931600,
            "apparentTemperatureMin": 51.35,
            "apparentTemperatureMinTime": 1493895600,
            "apparentTemperatureMax": 75.5,
            "apparentTemperatureMaxTime": 1493931600,
            "dewPoint": 48.98,
            "humidity": 0.63,
            "windSpeed": 14.54,
            "windBearing": 334,
            "visibility": 10,
            "cloudCover": 0.29,
            "pressure": 1017.68,
            "ozone": 351.34
        }, {
            "time": 1493960400,
            "summary": "Clear throughout the day.",
            "icon": "clear-day",
            "sunriseTime": 1493984338,
            "sunsetTime": 1494033304,
            "moonPhase": 0.34,
            "precipIntensity": 0,
            "precipIntensityMax": 0,
            "precipProbability": 0,
            "temperatureMin": 49.2,
            "temperatureMinTime": 1493982000,
            "temperatureMax": 76.74,
            "temperatureMaxTime": 1494018000,
            "apparentTemperatureMin": 45.73,
            "apparentTemperatureMinTime": 1493982000,
            "apparentTemperatureMax": 76.74,
            "apparentTemperatureMaxTime": 1494018000,
            "dewPoint": 47.69,
            "humidity": 0.59,
            "windSpeed": 8.24,
            "windBearing": 342,
            "cloudCover": 0,
            "pressure": 1018.08,
            "ozone": 337.46
        }, {
            "time": 1494046800,
            "summary": "Clear throughout the day.",
            "icon": "clear-day",
            "sunriseTime": 1494070686,
            "sunsetTime": 1494119749,
            "moonPhase": 0.37,
            "precipIntensity": 0,
            "precipIntensityMax": 0,
            "precipProbability": 0,
            "temperatureMin": 45.75,
            "temperatureMinTime": 1494068400,
            "temperatureMax": 79.85,
            "temperatureMaxTime": 1494104400,
            "apparentTemperatureMin": 45.75,
            "apparentTemperatureMinTime": 1494068400,
            "apparentTemperatureMax": 79.85,
            "apparentTemperatureMaxTime": 1494104400,
            "dewPoint": 50.88,
            "humidity": 0.65,
            "windSpeed": 5.25,
            "windBearing": 131,
            "cloudCover": 0,
            "pressure": 1016.31,
            "ozone": 328.92
        }, {
            "time": 1494133200,
            "summary": "Partly cloudy starting in the evening.",
            "icon": "partly-cloudy-night",
            "sunriseTime": 1494157035,
            "sunsetTime": 1494206194,
            "moonPhase": 0.4,
            "precipIntensity": 0.0007,
            "precipIntensityMax": 0.0022,
            "precipIntensityMaxTime": 1494201600,
            "precipProbability": 0.06,
            "precipType": "rain",
            "temperatureMin": 52.62,
            "temperatureMinTime": 1494154800,
            "temperatureMax": 85.63,
            "temperatureMaxTime": 1494190800,
            "apparentTemperatureMin": 52.62,
            "apparentTemperatureMinTime": 1494154800,
            "apparentTemperatureMax": 85.9,
            "apparentTemperatureMaxTime": 1494190800,
            "dewPoint": 56.26,
            "humidity": 0.63,
            "windSpeed": 11.72,
            "windBearing": 179,
            "cloudCover": 0.07,
            "pressure": 1012.79,
            "ozone": 321.8
        }, {
            "time": 1494219600,
            "summary": "Clear throughout the day.",
            "icon": "clear-day",
            "sunriseTime": 1494243384,
            "sunsetTime": 1494292639,
            "moonPhase": 0.43,
            "precipIntensity": 0.0009,
            "precipIntensityMax": 0.0016,
            "precipIntensityMaxTime": 1494284400,
            "precipProbability": 0.03,
            "precipType": "rain",
            "temperatureMin": 56.91,
            "temperatureMinTime": 1494241200,
            "temperatureMax": 83.6,
            "temperatureMaxTime": 1494277200,
            "apparentTemperatureMin": 56.91,
            "apparentTemperatureMinTime": 1494241200,
            "apparentTemperatureMax": 85.11,
            "apparentTemperatureMaxTime": 1494277200,
            "dewPoint": 61.22,
            "humidity": 0.72,
            "windSpeed": 10.57,
            "windBearing": 175,
            "cloudCover": 0.03,
            "pressure": 1014.51,
            "ozone": 316.91
        }]
    },
    "flags": {
        "sources": ["lamp", "gfs", "cmc", "nam", "rap", "rtma", "sref", "fnmoc", "isd", "madis", "nearest-precip", "nwspa", "darksky"],
        "lamp-stations": ["KADS", "KAFW", "KCPT", "KDAL", "KDFW", "KDTO", "KFTW", "KFWS", "KGKY", "KGPM", "KJWY", "KLNC", "KLUD", "KNFW", "KRBD", "KXBP"],
        "isd-stations": ["722094-53984", "722094-99999", "722479-53907", "722479-99999", "722580-13960", "722585-93901", "722589-03991", "722589-99999", "722590-03927", "722593-03985", "722594-53909", "722594-99999", "722595-13911", "722596-13961", "999999-03927", "999999-93901"],
        "madis-stations": ["AN595", "AN596", "AR768", "AU133", "D4887", "D8985", "E3096", "E3182", "E4609", "E6553", "E8881", "FWOT2", "KAFW", "KFTW", "UR242", "UR364"],
        "units": "us"
    }
}